tpg_invoice.py
tpg_invoice-0.1.3.dist-info/DESCRIPTION.rst
tpg_invoice-0.1.3.dist-info/METADATA
tpg_invoice-0.1.3.dist-info/RECORD
tpg_invoice-0.1.3.dist-info/WHEEL
tpg_invoice-0.1.3.dist-info/entry_points.txt
tpg_invoice-0.1.3.dist-info/metadata.json
tpg_invoice-0.1.3.dist-info/top_level.txt
