Metadata-Version: 2.0
Name: tpg-invoice
Version: 0.1.3
Summary: Extracts invoices from the TPG website.
Home-page: https://github.com/micolous/tpg_invoice
Author: micolous
Author-email: micolous+git@gmail.com
License: Apache-2.0
Platform: UNKNOWN
Classifier: Environment :: Console
Classifier: Intended Audience :: Telecommunications Industry
Classifier: License :: OSI Approved :: Apache Software License
Classifier: Programming Language :: Python
Classifier: Programming Language :: Python :: 3.6
Classifier: Programming Language :: Python :: Implementation :: CPython
Classifier: Programming Language :: Python :: Implementation :: PyPy
Classifier: Topic :: Office/Business :: Financial
Classifier: Topic :: Utilities
Requires-Dist: beautifulsoup4
Requires-Dist: requests
